reddutils/__init__.py
reddutils/example.py
reddutils/correlator/__init__.py
reddutils/exodus/__init__.py
reddutils/fourier/__init__.py
reddutils/owoifier/__init__.py
reddutils/periodogram/__init__.py
reddutils_test-1.0.0.dist-info/LICENSE
reddutils_test-1.0.0.dist-info/METADATA
reddutils_test-1.0.0.dist-info/WHEEL
reddutils_test-1.0.0.dist-info/top_level.txt
reddutils_test-1.0.0.dist-info/RECORD
